wkutils/__init__.py
wkutils-0.1.1.dist-info/METADATA
wkutils-0.1.1.dist-info/WHEEL
wkutils-0.1.1.dist-info/top_level.txt
wkutils-0.1.1.dist-info/RECORD
