Metadata-Version: 2.1
Name: wkutils
Version: 0.1.1
Summary: Useful utilities for python
Author: Werner Kruger
Author-email: <python@wkruger.com>
Keywords: python,utilities,financial,calculator
Classifier: Development Status :: 1 - Planning
Classifier: Intended Audience :: Developers
Classifier: Programming Language :: Python :: 3
Classifier: Operating System :: Unix
Classifier: Operating System :: MacOS :: MacOS X
Classifier: Operating System :: Microsoft :: Windows
Requires-Dist: numpy-financial
